README.md
setup.py
cool_lib/__init__.py
cool_lib/__main__.py
cool_lib/a.py
cool_lib/b.py
cool_lib_test_kxyz.egg-info/PKG-INFO
cool_lib_test_kxyz.egg-info/SOURCES.txt
cool_lib_test_kxyz.egg-info/dependency_links.txt
cool_lib_test_kxyz.egg-info/entry_points.txt
cool_lib_test_kxyz.egg-info/not-zip-safe
cool_lib_test_kxyz.egg-info/top_level.txt